<?xml version="1.0" encoding="utf-8"?>
<Root>
  <Sets>
    <Ground FileName="objects.xml" />
  </Sets>
  <Music Name="music_pk" Volume="0.3" />
  <Coins Value="50" />
  <Objects Name="Money" />
  <Track>
    <Object Factor="1">
      <Content>
        <Image X="-230" Y="-102" ClassName="cons_barrel" Width="64" Height="82" NativeX="64" NativeY="82">
          <Properties>
            <Static>
              <Selection Choice="AITriggers" Variant="HunterMode" />
            </Static>
          </Properties>
        </Image>
        <Image X="-395" Y="-117" ClassName="cons_barrel" Width="64" Height="82" NativeX="64" NativeY="82" />
        <Image X="-68" Y="-111" ClassName="cons_barrel" Width="92.97998" Height="78.86913" NativeX="64" NativeY="82">
          <Properties>
            <Static>
              <Matrix A="12.579580" B="62.751530" C="-80.400400" D="16.117580" Tx="80.400400" Ty="0.000000" />
              <StartColor Color="#8FFF00FF" />
              <Selection Choice="AITriggers" Variant="CommonMode" />
            </Static>
          </Properties>
        </Image>
        <Item X="-366" Y="-83" Type="1" Radius="80" Score="10" GroupId="1" />
        <Platform X="31" Y="7" Width="500" Height="100" />
        <Spawn X="-565" Y="-202" Name="PlayerSpawn" Animation="JumpOff|18" />
        <Camera X="0" Y="0" />
      </Content>
    </Object>
  </Track>
</Root>